decorify/__init__.py
decorify/base.py
decorify/basic.py
decorify/exceptions.py
decorify/io_redirect.py
decorify/iterative.py
decorify/plot.py
decorify/profiling.py
decorify-0.1.2.dist-info/LICENSE
decorify-0.1.2.dist-info/METADATA
decorify-0.1.2.dist-info/WHEEL
decorify-0.1.2.dist-info/RECORD
