Metadata-Version: 2.1
Name: decorify
Version: 0.1.2
Summary: Simple light-weight Python library with handy for every day use decorators
Home-page: https://github.com/Dawid64/decorify
Author: Dawid Siera
Author-email: dawid.siera@gmail.com
Classifier: Programming Language :: Python :: 2
Classifier: Programming Language :: Python :: 2.7
Classifier: Programming Language :: Python :: 3
Classifier: Programming Language :: Python :: 3.4
Classifier: Programming Language :: Python :: 3.5
Classifier: Programming Language :: Python :: 3.6
Classifier: Programming Language :: Python :: 3.7
Classifier: Programming Language :: Python :: 3.8
Classifier: Programming Language :: Python :: 3.9
Classifier: Programming Language :: Python :: 3.10
Classifier: Programming Language :: Python :: 3.11
Classifier: Programming Language :: Python :: 3.12
Classifier: Programming Language :: Python :: 3.13
Provides-Extra: plot
Project-URL: Repository, https://github.com/Dawid64/decorify
